tpl/__init__.py
tpl/__main__.py
tpl/__version__.py
tpl-0.10.dist-info/METADATA
tpl-0.10.dist-info/WHEEL
tpl-0.10.dist-info/entry_points.txt
tpl-0.10.dist-info/licenses/LICENSE
tpl-0.10.dist-info/RECORD
