Metadata-Version: 2.3
Name: tpl
Version: 0.10
Summary: Render templates with data from various sources
Project-URL: Homepage, https://github.com/m3t0r/tpl
Author-email: Simon Lutz Brüggen <tpl@m3t0r.de>
License: MIT License
License-File: LICENSE
Classifier: Development Status :: 4 - Beta
Classifier: Environment :: Console
Classifier: Intended Audience :: Developers
Classifier: Intended Audience :: System Administrators
Classifier: License :: OSI Approved :: MIT License
Classifier: Operating System :: Unix
Classifier: Programming Language :: Python :: 3
Requires-Python: >=3.9
Requires-Dist: jinja2>=2.10.1
Requires-Dist: pyyaml>=3.13
